textualodon/__init__.py
textualodon/api.py
textualodon/app_logo.py
textualodon/constants.py
textualodon/login_form.py
textualodon/main.py
textualodon/new_post_form.py
textualodon/poll.py
textualodon/post_details.py
textualodon/posts.py
textualodon/screens.py
textualodon/style.css
textualodon/textualodon.py
textualodon/timelines.py
textualodon/trendings.py
textualodon-0.2.1.dist-info/LICENSE
textualodon-0.2.1.dist-info/METADATA
textualodon-0.2.1.dist-info/WHEEL
textualodon-0.2.1.dist-info/entry_points.txt
textualodon-0.2.1.dist-info/top_level.txt
textualodon-0.2.1.dist-info/RECORD
