Metadata-Version: 2.1
Name: textualodon
Version: 0.2.1
Summary: Mastodon client for terminal. Created with an excellent Textual framework.
Author: djvdq
Maintainer: djvdq
License: MIT License
Project-URL: repository, https://codeberg.org/djvdq/Textualodon
Classifier: Development Status :: 2 - Pre-Alpha
Classifier: Programming Language :: Python :: 3.9
Classifier: Programming Language :: Python :: 3.10
Classifier: Programming Language :: Python :: 3.11
Classifier: Programming Language :: Python :: 3.12
Classifier: Operating System :: OS Independent
Classifier: Environment :: Console
Requires-Python: >=3.9
License-File: LICENSE
Requires-Dist: beautifulsoup4==4.12.2
Requires-Dist: requests==2.31.0
Requires-Dist: textual==0.79.1
Provides-Extra: dev
Requires-Dist: pre-commit; extra == "dev"
Requires-Dist: flake8; extra == "dev"
Requires-Dist: flake8-import-order; extra == "dev"
Requires-Dist: flake8-bugbear; extra == "dev"
Requires-Dist: flake8-simplify; extra == "dev"
Requires-Dist: flake8-comprehensions; extra == "dev"
Requires-Dist: flake8-builtins; extra == "dev"
Requires-Dist: flake8-annotations; extra == "dev"
Requires-Dist: black; extra == "dev"
Requires-Dist: mypy; extra == "dev"
Requires-Dist: textual-dev; extra == "dev"
